indentedlogs/__init__.py
indentedlogs/formatters.py
indentedlogs/monitor.py
indentedlogs/utils.py
indentedlogs-0.1.4.dist-info/LICENSE
indentedlogs-0.1.4.dist-info/WHEEL
indentedlogs-0.1.4.dist-info/METADATA
indentedlogs-0.1.4.dist-info/RECORD
