Metadata-Version: 2.1
Name: indentedlogs
Version: 0.1.4
Summary: Adds indentation to the log messages according to their location in the call stack.
Home-page: https://gergelyk.github.io/python-indentedlogs
License: MIT
Keywords: logging,log,tracing,trace,indented,indent
Author: Grzegorz Krasoń
Author-email: grzegorz.krason@gmail.com
Requires-Python: >=3.8,<4.0
Classifier: License :: OSI Approved :: MIT License
Classifier: Programming Language :: Python :: 3
Classifier: Programming Language :: Python :: 3.8
Project-URL: Documentation, https://gergelyk.github.io/python-indentedlogs
Project-URL: Repository, https://github.com/gergelyk/python-indentedlogs
